README.rst
dbg.py
setup.py
dbghelper.egg-info/PKG-INFO
dbghelper.egg-info/SOURCES.txt
dbghelper.egg-info/dependency_links.txt
dbghelper.egg-info/requires.txt
dbghelper.egg-info/top_level.txt