Metadata-Version: 1.0
Name: dbghelper
Version: 0.2.1
Summary: Simple helper for inline winpdb/pdb debugging
Home-page: https://github.com/davidfraser/dbghelper
Author: David Fraser
Author-email: davidf@sjsoft.com
License: BSD
Platform: UNKNOWN
